jsbucket/__init__.py
jsbucket/__main__.py
jsbucket/core.py
jsbucket/jsbucket.py
jsbucket-2.7.5.dist-info/licenses/LICENSE
jsbucket-2.7.5.dist-info/METADATA
jsbucket-2.7.5.dist-info/WHEEL
jsbucket-2.7.5.dist-info/entry_points.txt
jsbucket-2.7.5.dist-info/top_level.txt
jsbucket-2.7.5.dist-info/RECORD
