Metadata-Version: 2.4
Name: jsbucket
Version: 2.7.5
Summary: A tool to discover S3 buckets from subdomains by analyzing JavaScript files.
Home-page: https://github.com/saeed0xf/jsbucket
Author: Mortaza Behesti Al Saeed
Author-email: Mortaza Behesti Al Saeed <saeed.ctf@gmail.com>
Project-URL: Homepage, https://github.com/saeed0xf/jsbucket
Project-URL: Repository, https://github.com/saeed0xf/jsbucket
Project-URL: Issues, https://github.com/saeed0xf/jsbucket/issues
Project-URL: Documentation, https://github.com/saeed0xf/jsbucket/blob/main/README.md
Keywords: security,s3,bucket,discovery,javascript,subdomain,bugbounty,pentest
Classifier: Programming Language :: Python :: 3
Classifier: Programming Language :: Python :: 3.6
Classifier: Programming Language :: Python :: 3.7
Classifier: Programming Language :: Python :: 3.8
Classifier: Programming Language :: Python :: 3.9
Classifier: Programming Language :: Python :: 3.10
Classifier: Programming Language :: Python :: 3.11
Classifier: Programming Language :: Python :: 3.12
Classifier: Operating System :: OS Independent
Classifier: Development Status :: 4 - Beta
Classifier: Intended Audience :: Developers
Classifier: Intended Audience :: Information Technology
Classifier: Topic :: Security
Classifier: Topic :: Internet :: WWW/HTTP
Requires-Python: >=3.6
License-File: LICENSE
Requires-Dist: requests
Requires-Dist: tqdm
Requires-Dist: rich
Requires-Dist: tldextract
Dynamic: author
Dynamic: home-page
Dynamic: license-file
Dynamic: requires-python
